physical_ai_interpretability/__init__.py
physical_ai_interpretability/attention_maps/__init__.py
physical_ai_interpretability/attention_maps/act_attention_mapper.py
physical_ai_interpretability/ood/__init__.py
physical_ai_interpretability/ood/ood_detector.py
physical_ai_interpretability/sae/__init__.py
physical_ai_interpretability/sae/activation_collector.py
physical_ai_interpretability/sae/builder.py
physical_ai_interpretability/sae/config.py
physical_ai_interpretability/sae/sae.py
physical_ai_interpretability/sae/token_sampler.py
physical_ai_interpretability/sae/trainer.py
physical_ai_interpretability/utils/__init__.py
physical_ai_interpretability/utils/dataset_factory.py
physical_ai_interpretability/utils/naming.py
physical_ai_interpretability-0.1.2.dist-info/licenses/LICENSE
physical_ai_interpretability-0.1.2.dist-info/METADATA
physical_ai_interpretability-0.1.2.dist-info/WHEEL
physical_ai_interpretability-0.1.2.dist-info/top_level.txt
physical_ai_interpretability-0.1.2.dist-info/RECORD
