Metadata-Version: 2.4
Name: physical-ai-interpretability
Version: 0.1.2
Summary: Tools for interpretability analysis of physical AI models, including sparse autoencoders and attention mapping
Author: Ville Kuosmanen
License: MIT License
Project-URL: Homepage, https://github.com/villekuosmanen/physical-ai-interpretability
Project-URL: Repository, https://github.com/villekuosmanen/physical-ai-interpretability
Project-URL: Issues, https://github.com/villekuosmanen/physical-ai-interpretability/issues
Classifier: Development Status :: 3 - Alpha
Classifier: Intended Audience :: Science/Research
Classifier: License :: OSI Approved :: MIT License
Classifier: Programming Language :: Python :: 3
Classifier: Programming Language :: Python :: 3.10
Classifier: Programming Language :: Python :: 3.11
Classifier: Topic :: Scientific/Engineering :: Artificial Intelligence
Classifier: Topic :: Scientific/Engineering :: Visualization
Requires-Python: >=3.10
License-File: LICENSE
Requires-Dist: torch>=1.12.0
Requires-Dist: numpy>=1.20.0
Requires-Dist: tqdm>=4.60.0
Requires-Dist: safetensors>=0.3.0
Requires-Dist: pandas>=1.3.0
Requires-Dist: scipy
Requires-Dist: huggingface_hub
Requires-Dist: opencv-python>=4.5.0
Requires-Dist: wandb>=0.12.0
Requires-Dist: lerobot
Requires-Dist: dataclasses; python_version < "3.9"
Provides-Extra: dev
Requires-Dist: pytest>=6.0; extra == "dev"
Requires-Dist: pytest-cov>=2.0; extra == "dev"
Requires-Dist: black>=22.0; extra == "dev"
Requires-Dist: isort>=5.0; extra == "dev"
Requires-Dist: flake8>=4.0; extra == "dev"
Requires-Dist: mypy>=0.900; extra == "dev"
Provides-Extra: notebooks
Requires-Dist: jupyter>=1.0.0; extra == "notebooks"
Requires-Dist: matplotlib>=3.5.0; extra == "notebooks"
Requires-Dist: seaborn>=0.11.0; extra == "notebooks"
Requires-Dist: plotly>=5.0.0; extra == "notebooks"
Provides-Extra: visualization
Requires-Dist: matplotlib>=3.5.0; extra == "visualization"
Requires-Dist: seaborn>=0.11.0; extra == "visualization"
Requires-Dist: plotly>=5.0.0; extra == "visualization"
Provides-Extra: docs
Requires-Dist: sphinx>=4.0.0; extra == "docs"
Requires-Dist: sphinx-rtd-theme>=1.0.0; extra == "docs"
Dynamic: license-file
